py_vollib_vectorized/__init__.py
py_vollib_vectorized/_iv_models.py
py_vollib_vectorized/_model_calls.py
py_vollib_vectorized/_numerical_greeks.py
py_vollib_vectorized/api.py
py_vollib_vectorized/greeks.py
py_vollib_vectorized/implied_volatility.py
py_vollib_vectorized/models.py
py_vollib_vectorized/util/__init__.py
py_vollib_vectorized/util/data_format.py
py_vollib_vectorized/util/greeks_helpers.py
py_vollib_vectorized/util/jit_helper.py
tests/__init__.py
tests/test_entrypoints.py
tests/test_monkeypatch.py
py_vollib_vectorized-0.1.1.dist-info/LICENSE
py_vollib_vectorized-0.1.1.dist-info/METADATA
py_vollib_vectorized-0.1.1.dist-info/WHEEL
py_vollib_vectorized-0.1.1.dist-info/top_level.txt
py_vollib_vectorized-0.1.1.dist-info/RECORD
