Metadata-Version: 2.1
Name: py-vollib-vectorized
Version: 0.1.1
Summary: A fast, vectorized approach to calculating Implied Volatility and Greeks using the Black, Black-Scholes and Black-Scholes-Merton pricing.
Home-page: https://github.com/marcdemers/py_vollib_vectorized
Author: Marc Demers
Author-email: demers.marc@gmail.com
License: MIT
Platform: UNKNOWN
Classifier: Development Status :: 4 - Beta
Classifier: Intended Audience :: Developers
Classifier: Intended Audience :: Financial and Insurance Industry
Classifier: Intended Audience :: Science/Research
Classifier: Topic :: Scientific/Engineering
Classifier: Topic :: Scientific/Engineering :: Mathematics
Classifier: Topic :: Scientific/Engineering :: Information Analysis
Classifier: Topic :: Software Development :: Libraries
Classifier: Programming Language :: Python :: 3.3
Classifier: Programming Language :: Python :: 3.4
Classifier: Programming Language :: Python :: 3.5
Classifier: Programming Language :: Python :: 3.6
Classifier: Programming Language :: Python :: 3.7
Classifier: Programming Language :: Python :: Implementation
Classifier: License :: OSI Approved :: MIT License
Classifier: Topic :: Office/Business :: Financial
Classifier: Topic :: Office/Business :: Financial :: Investment
Requires-Dist: py-vollib (>=1.0.1)
Requires-Dist: numba (>=0.51.0)
Requires-Dist: py-lets-be-rational
Requires-Dist: numpy
Requires-Dist: pandas
Requires-Dist: scipy
